doors/__init__.py
doors/bq.py
doors/clargs.py
doors/cleaning.py
doors/dates.py
doors/debug.py
doors/dicts.py
doors/download.py
doors/eda.py
doors/features.py
doors/inout.py
doors/mem.py
doors/metrics.py
doors/modelling.py
doors/models.py
doors/multifeat.py
doors/np.py
doors/outliers.py
doors/paths.py
doors/plots.py
doors/setup_logger.py
doors/stats.py
doors/strings.py
doors/univariate.py
doors/venn.py
doors-0.2.4.dist-info/LICENCE.txt
doors-0.2.4.dist-info/METADATA
doors-0.2.4.dist-info/WHEEL
doors-0.2.4.dist-info/RECORD
